parameters.v
/////		CLOCK PARAMETERS	/////
`define DUTY        5			
`define PERIOD      10		
`define NUM_CYCLES  500				// Testbenching: The number of cycles the testbench should perform before stopping.

/////		STATES			/////
`define NUM_STATES 4
`define	RESET    0			
`define FETCH    1
`define DECODE   2
`define EXECUTE  3
`define WAIT     4

/////		BUS WIDTHS		/////
`define OPCODE_WIDTH  3
`define ADDR_WIDTH    6
`define DATA_WIDTH    6
`define INST_WIDTH    21
`define MEM_WIDTH     27

/////		MEMORY PARAMETERS	/////
`define NUM_MEM_ADDR  64			// Number of memory address.
`define NUM_REG_ADDR  8				// Number of registers.
`define MAX_ADDR_VAL  64			// Maximum address value an address bus can carry
`define MAX_DATA_VAL  64			// Maximum data value an data bus can carry

/////		OPCODES			/////
`define DONE 	 0				// No more instructions in memory.
`define LOAD_M 	 1				// Loads a register with an memory address's value.
`define LOAD_I 	 2				// Loads a register with a immediate value.
`define LOAD_PC  3				// Load the program counter with a value.
`define STORE	 4				// Stores the value of a register into memory.
`define ADD	 5				// Performs addition between two register values.
`define SUB	 6				// Performs subtraction between two register values.
`define MUL	 7				// Performs multiplication between two register values.

/////		RANGES			/////
`define OPCODE_UPPER_BIT  21			// Opcode upper bit in an instruction.
`define OPCODE_LOWER_BIT  18 			// Opcode lower bit in an instruction.
`define REG1_UPPER_BIT  18			// Source_Reg1 upper bit in an instruction.
`define REG1_LOWER_BIT  12 			// Source_Reg1 lower bit in an instruction.
`define REG2_UPPER_BIT  12			// Source_Reg2 upper bit in an instruction.
`define REG2_LOWER_BIT  6			// Source_Reg2 lower bit in an instruction.
`define DREG_UPPER_BIT  6			// Dest_Reg upper bit in an instruction.
`define DREG_LOWER_BIT  0			// Dest_Reg lower bit in an instruction.

////		TESTING			////
/*
	WARNING: Random Number Generator Bounds
		- Upper bound CANNOT exceed pow(2, ADDR_WIDTH) OR be negative.
		- Lower bound CANNOT exceed pow(2, ADDR_WIDTH) OR be negative.
*/
//// ALU
`define NUM_ALU_TEST 64				// Number of tests the Alu will perform.
`define REG_UPPER_BOUND 64			// Upper bound of the random number generator.
`define REG_LOWER_BOUND 0			// Lower bound of the random number generator.

// CONTROLLER
`define NUM_CONTROLLER_TEST 64			// Number of tests the Controller will perform.
`define CONT_GEN_RAND_OPCODE 1'b0		// Selects whether to randomize the inputs or use the file input.

// IR
`define NUM_IR_TEST 64				// Upper bound of the random number generator.
`define IR_GEN_RAND_INST 1			// Lower bound of the random number generator.

// MUX
`define NUM_MUX_TEST  64			// Number of tests the Mux will perform.
`define MUX_UPPER_BOUND 64			// Upper bound of the random number generator.
`define MUX_LOWER_BOUND 0			// Lower bound of the random number generator.

// PC
`define NUM_PC_TEST 64				// Number of tests the PC will perform.
`define DREG_UPPER_BOUND 64			// Upper bound of the random number generator.
`define DREG_LOWER_BOUND 0			// Lower bound of the random number generator.

// RAM
`define NUM_RAM_TEST 64				// Number of tests the RAM will perform.
`define RAM_GEN_RAND_INPUT 1'b1			// Selects whether to randomize the inputs or use the file input.

Modules/ALU.v
// Arithmetic Logic Unit
module ALU(Alu_Add, Alu_Sub, Alu_Mul, Alu_Pass, Reg1_Out, Reg2_Out, Alu_Out); 
	`include "parameters.v"	
	/*
		Control Signals:
			Alu_Add : Performs addition between the to Source_Reg values
			Alu_Sub : Performs subtraction between the to Source_Reg values
			Alu_Mul : Performs multiplication between the to Source_Reg values
			Alu_Pass : Passes Source_Reg2 into Alu_Out
	*/
	input Alu_Add, Alu_Sub, Alu_Mul, Alu_Pass;
	/*
		Input Registers:
			Source_Reg1 : Operand 1
			Reg2_Out :    Operand 2 and is used for the value to be stored in memory 
	*/
	input [`DATA_WIDTH-1:0] Reg1_Out, Reg2_Out;
	//	Output
	output reg [`DATA_WIDTH-1:0] Alu_Out;
	
	always @(*) begin
		if(Alu_Add) 	  Alu_Out = Reg1_Out + Reg2_Out;
		else if(Alu_Sub)  Alu_Out = Reg1_Out - Reg2_Out;
		else if(Alu_Mul)  Alu_Out = Reg1_Out * Reg2_Out;
		else if(Alu_Pass) Alu_Out = Reg2_Out;
		else		  Alu_Out = 0;
	end
endmodule

Testbenches/ALU_tb.v
module ALU_tb();
	`include "parameters.v"

	/*
		Control Signals:
			Alu_Add - Performs addition between Reg1_Out & Reg2_Out.
			Alu_Sub - Performs subtraction between Reg1_Out & Reg2_Out.
			Alu_Mul - Performs multiplication between Reg1_Out & Reg2_Out.
			Alu_Padd - Passes Reg2_Out to Alu_Out.
	*/
	reg Alu_Add=0, Alu_Sub=0, Alu_Mul=0, Alu_Pass=0;
	/*
		Inputs:
			Reg1_Out - Operand 1.
			Reg2_Out - Operand 2 or value to be stored in memory.
	*/
	reg [`DATA_WIDTH-1:0] Reg1_Out=0, Reg2_Out=0;

	/*
		Output:
			Alu_Out - Output from the ALU.
	*/
        wire [`DATA_WIDTH-1:0] Alu_Out;
	
	ALU arithmetic_logic_unit(
		.Alu_Add(Alu_Add),
		.Alu_Sub(Alu_Sub),
		.Alu_Mul(Alu_Mul),
		.Alu_Pass(Alu_Pass),
		.Reg1_Out(Reg1_Out),
		.Reg2_Out(Reg2_Out),
		.Alu_Out(Alu_Out)
	);
	
	integer file;
	integer test;
	integer operation;
	initial begin
		$dumpfile("Junk/ALU.vcd");
		$dumpvars(0, ALU_tb);
		file = $fopen("Results/ALU.r", "w");
		for(test = 0; test < `NUM_ALU_TEST; test = test + 1) begin
			operation = $urandom % 4;	// Used to determine what operation is perform
			if(operation == 0) 
				Alu_Add = 1;
			else if(operation == 1) 
				Alu_Sub = 1;
			else if(operation == 2) 
				Alu_Mul = 1;
			else if(operation == 3) 
				Alu_Pass = 1;
			Reg1_Out = $urandom % (`REG_UPPER_BOUND-`REG_LOWER_BOUND+1) + `REG_LOWER_BOUND;	
			Reg2_Out = $urandom % (`REG_UPPER_BOUND-`REG_LOWER_BOUND+1) + `REG_LOWER_BOUND;	
			#5;
			$fwrite(file, "Test = %d", test);	
			$fwrite(file, "\tAlu_Add = %b", Alu_Add);	
			$fwrite(file, "\tAlu_Sub = %b", Alu_Sub);	
			$fwrite(file, "\tAlu_Mul = %b", Alu_Mul);	
			$fwrite(file, "\tAlu_Pass = %b", Alu_Pass);	
			$fwrite(file, "\tReg1_Out = %d", Reg1_Out);	
			$fwrite(file, "\tReg2_Out = %d", Reg2_Out);	
			$fwrite(file, "\tAlu_Out = %d\n\n", Alu_Out);	
			Alu_Add = 0;
			Alu_Sub = 0;
			Alu_Mul = 0;
			Alu_Pass = 0;
		end
		$fclose(file);
		$finish();
		$stop;
	end
endmodule

Junk/ALU.vcd
$date
	Sat Dec 16 12:28:40 2023
$end
$version
	Icarus Verilog
$end
$timescale
	1s
$end
$scope module ALU_tb $end
$var wire 6 ! Alu_Out [5:0] $end
$var reg 1 " Alu_Add $end
$var reg 1 # Alu_Mul $end
$var reg 1 $ Alu_Pass $end
$var reg 1 % Alu_Sub $end
$var reg 6 & Reg1_Out [5:0] $end
$var reg 6 ' Reg2_Out [5:0] $end
$var integer 32 ( file [31:0] $end
$var integer 32 ) operation [31:0] $end
$var integer 32 * test [31:0] $end
$scope module arithmetic_logic_unit $end
$var wire 1 " Alu_Add $end
$var wire 1 # Alu_Mul $end
$var wire 1 $ Alu_Pass $end
$var wire 1 % Alu_Sub $end
$var wire 6 + Reg1_Out [5:0] $end
$var wire 6 , Reg2_Out [5:0] $end
$var reg 6 - Alu_Out [5:0] $end
$upscope $end
$upscope $end
$enddefinitions $end
#0
$dumpvars
b11101 -
b100010 ,
b111011 +
b0 *
b0 )
b10000000000000000000000000000011 (
b100010 '
b111011 &
0%
0$
0#
1"
b11101 !
$end
#5
b101101 !
b101101 -
b101101 '
b101101 ,
b1111 &
b1111 +
1$
b11 )
b1 *
0"
#10
b101 !
b101 -
b110110 '
b110110 ,
b111011 &
b111011 +
1%
b1 )
b10 *
0$
#15
b1 !
b1 -
b11110 '
b11110 ,
b11111 &
b11111 +
b11 *
1%
#20
b11011 !
b11011 -
b101010 '
b101010 ,
b101 &
b101 +
b100 *
1%
#25
b101000 !
b101000 -
b101100 '
b101100 ,
b1110 &
b1110 +
1#
b10 )
b101 *
0%
#30
b110111 !
b110111 -
b100100 '
b100100 ,
b11011 &
b11011 +
1%
b1 )
b110 *
0#
#35
b100101 !
b100101 -
b100101 '
b100101 ,
b111011 &
b111011 +
1$
b11 )
b111 *
0%
#40
b101111 !
b101111 -
b10001 '
b10001 ,
b11110 &
b11110 +
1"
b0 )
b1000 *
0$
#45
b101000 !
b101000 -
b110 '
b110 ,
b101110 &
b101110 +
1%
b1 )
b1001 *
0"
#50
b11001 !
b11001 -
b11001 '
b11001 ,
b1101 &
b1101 +
1$
b11 )
b1010 *
0%
#55
b11110 !
b11110 -
b10010 '
b10010 ,
b1100 &
b1100 +
1"
b0 )
b1011 *
0$
#60
b111000 !
b111000 -
b1000 '
b1000 ,
b10111 &
b10111 +
1#
b10 )
b1100 *
0"
#65
b1100 !
b1100 -
b1100 '
b1100 ,
b111111 &
b111111 +
1$
b11 )
b1101 *
0#
#70
b100000 !
b100000 -
b100 '
b100 ,
b11000 &
b11000 +
1#
b10 )
b1110 *
0$
#75
b1101 !
b1101 -
b1101 '
b1101 ,
b110010 &
b110010 +
1$
b11 )
b1111 *
0#
#80
b100100 !
b100100 -
b100010 '
b100010 ,
1#
b10 )
b10000 *
0$
#85
b10000 !
b10000 -
b10000 '
b10000 ,
b101101 &
b101101 +
b10001 *
1#
#90
b110 !
b110 -
b101 '
b101 ,
b1 &
b1 +
1"
b0 )
b10010 *
0#
#95
b0 !
b0 -
b0 '
b0 ,
b101100 &
b101100 +
1#
b10 )
b10011 *
0"
#100
b101111 !
b101111 -
b101101 '
b101101 ,
b10 &
b10 +
1"
b0 )
b10100 *
0#
#105
b11111 !
b11111 -
b1000 '
b1000 ,
b100111 &
b100111 +
1%
b1 )
b10101 *
0"
#110
b11101 !
b11101 -
b11101 '
b11101 ,
b101010 &
b101010 +
1$
b11 )
b10110 *
0%
#115
b101001 !
b101001 -
b110001 '
b110001 ,
b11010 &
b11010 +
1%
b1 )
b10111 *
0$
#120
b101010 !
b101010 -
b10 '
b10 ,
b10101 &
b10101 +
1#
b10 )
b11000 *
0%
#125
b110010 !
b110010 -
b110010 '
b110010 ,
b1000 &
b1000 +
1$
b11 )
b11001 *
0#
#130
b10000 !
b10000 -
b10000 '
b10000 ,
b110011 &
b110011 +
b11010 *
1$
#135
b110101 !
b110101 -
b100111 '
b100111 ,
b11100 &
b11100 +
1%
b1 )
b11011 *
0$
#140
b101011 !
b101011 -
b101011 '
b101011 ,
b10110 &
b10110 +
1$
b11 )
b11100 *
0%
#145
b100 !
b100 -
b11011 '
b11011 ,
b101001 &
b101001 +
1"
b0 )
b11101 *
0$
#150
b111000 !
b111000 -
b111000 '
b111000 ,
b10111 &
b10111 +
1$
b11 )
b11110 *
0"
#155
b100101 !
b100101 -
b11111 '
b11111 ,
b111011 &
b111011 +
1#
b10 )
b11111 *
0$
#160
b100100 !
b100100 -
b100100 '
b100100 ,
b100101 &
b100101 +
1$
b11 )
b100000 *
0#
#165
b100000 !
b100000 -
b10000 '
b10000 ,
b10000 &
b10000 +
1"
b0 )
b100001 *
0$
#170
b101 !
b101 -
b101 '
b101 ,
b1000 &
b1000 +
1$
b11 )
b100010 *
0"
#175
b1010 !
b1010 -
b10010 '
b10010 ,
b111101 &
b111101 +
1#
b10 )
b100011 *
0$
#180
b101000 !
b101000 -
b1000 '
b1000 ,
b101 &
b101 +
b100100 *
1#
#185
b110110 !
b110110 -
b110110 '
b110110 ,
b11010 &
b11010 +
1$
b11 )
b100101 *
0#
#190
b1001 !
b1001 -
b1001 '
b1001 ,
b110110 &
b110110 +
b100110 *
1$
#195
b11011 !
b11011 -
b11011 '
b11011 ,
b111100 &
b111100 +
b100111 *
1$
#200
b101111 !
b101111 -
b110101 '
b110101 ,
b100100 &
b100100 +
1%
b1 )
b101000 *
0$
#205
b11011 !
b11011 -
b110100 '
b110100 ,
b1111 &
b1111 +
b101001 *
1%
#210
b10011 !
b10011 -
b101000 '
b101000 ,
b111011 &
b111011 +
b101010 *
1%
#215
b1101 !
b1101 -
b111001 '
b111001 ,
b110101 &
b110101 +
1#
b10 )
b101011 *
0%
#220
b110110 !
b110110 -
b101110 '
b101110 ,
b1000 &
b1000 +
1"
b0 )
b101100 *
0#
#225
b1110 !
b1110 -
b1110 '
b1110 ,
b110101 &
b110101 +
1$
b11 )
b101101 *
0"
#230
b111 !
b111 -
b111 '
b111 ,
b110 &
b110 +
b101110 *
1$
#235
b101100 !
b101100 -
b110010 '
b110010 ,
b111010 &
b111010 +
1"
b0 )
b101111 *
0$
#240
b10010 !
b10010 -
b111010 '
b111010 ,
b11000 &
b11000 +
b110000 *
1"
#245
b11001 !
b11001 -
b1001 '
b1001 ,
b100010 &
b100010 +
1%
b1 )
b110001 *
0"
#250
b101111 !
b101111 -
b110100 '
b110100 ,
b100011 &
b100011 +
b110010 *
1%
#255
b100100 !
b100100 -
b101001 '
b101001 ,
b100 &
b100 +
1#
b10 )
b110011 *
0%
#260
b111101 !
b111101 -
b11001 '
b11001 ,
b101 &
b101 +
b110100 *
1#
#265
b111 !
b111 -
b101100 '
b101100 ,
b110011 &
b110011 +
1%
b1 )
b110101 *
0#
#270
b10111 !
b10111 -
b1000 '
b1000 ,
b1111 &
b1111 +
1"
b0 )
b110110 *
0%
#275
b111000 !
b111000 -
b11000 '
b11000 ,
b11101 &
b11101 +
1#
b10 )
b110111 *
0"
#280
b11 !
b11 -
b10101 '
b10101 ,
b11000 &
b11000 +
1%
b1 )
b111000 *
0#
#285
b110110 !
b110110 -
b10001 '
b10001 ,
b10110 &
b10110 +
1#
b10 )
b111001 *
0%
#290
b101110 '
b101110 ,
b11101 &
b11101 +
b111010 *
1#
#295
b10100 !
b10100 -
b110010 '
b110010 ,
b11010 &
b11010 +
b111011 *
1#
#300
b111111 !
b111111 -
b10110 '
b10110 ,
b10101 &
b10101 +
1%
b1 )
b111100 *
0#
#305
b11010 !
b11010 -
b11010 '
b11010 ,
b101010 &
b101010 +
1$
b11 )
b111101 *
0%
#310
b11110 !
b11110 -
b11101 '
b11101 ,
b110110 &
b110110 +
1#
b10 )
b111110 *
0$
#315
b11001 !
b11001 -
b110011 '
b110011 ,
b100110 &
b100110 +
1"
b0 )
b111111 *
0#
#320
b0 !
b0 -
b1000000 *
0"
