parameters.v
/////		CLOCK PARAMETERS	/////
`define DUTY        5			
`define PERIOD      10		
`define NUM_CYCLES  500				// Testbenching: The number of cycles the testbench should perform before stopping.

/////		STATES			/////
`define NUM_STATES 4
`define	RESET    0			
`define FETCH    1
`define DECODE   2
`define EXECUTE  3
`define WAIT     4

/////		BUS WIDTHS		/////
`define OPCODE_WIDTH  3
`define ADDR_WIDTH    6
`define DATA_WIDTH    6
`define INST_WIDTH    21
`define MEM_WIDTH     27

/////		MEMORY PARAMETERS	/////
`define NUM_MEM_ADDR  64			// Number of memory address.
`define NUM_REG_ADDR  8				// Number of registers.
`define MAX_ADDR_VAL  64			// Maximum address value an address bus can carry
`define MAX_DATA_VAL  64			// Maximum data value an data bus can carry

/////		OPCODES			/////
`define DONE 	 0				// No more instructions in memory.
`define LOAD_M 	 1				// Loads a register with an memory address's value.
`define LOAD_I 	 2				// Loads a register with a immediate value.
`define LOAD_PC  3				// Load the program counter with a value.
`define STORE	 4				// Stores the value of a register into memory.
`define ADD	 5				// Performs addition between two register values.
`define SUB	 6				// Performs subtraction between two register values.
`define MUL	 7				// Performs multiplication between two register values.

/////		RANGES			/////
`define OPCODE_UPPER_BIT  21			// Opcode upper bit in an instruction.
`define OPCODE_LOWER_BIT  18 			// Opcode lower bit in an instruction.
`define REG1_UPPER_BIT  18			// Source_Reg1 upper bit in an instruction.
`define REG1_LOWER_BIT  12 			// Source_Reg1 lower bit in an instruction.
`define REG2_UPPER_BIT  12			// Source_Reg2 upper bit in an instruction.
`define REG2_LOWER_BIT  6			// Source_Reg2 lower bit in an instruction.
`define DREG_UPPER_BIT  6			// Dest_Reg upper bit in an instruction.
`define DREG_LOWER_BIT  0			// Dest_Reg lower bit in an instruction.

////		TESTING			////
/*
	WARNING: Random Number Generator Bounds
		- Upper bound CANNOT exceed pow(2, ADDR_WIDTH) OR be negative.
		- Lower bound CANNOT exceed pow(2, ADDR_WIDTH) OR be negative.
*/
//// ALU
`define NUM_ALU_TEST 64				// Number of tests the Alu will perform.
`define REG_UPPER_BOUND 64			// Upper bound of the random number generator.
`define REG_LOWER_BOUND 0			// Lower bound of the random number generator.

// CONTROLLER
`define NUM_CONTROLLER_TEST 64			// Number of tests the Controller will perform.
`define CONT_GEN_RAND_OPCODE 1'b0		// Selects whether to randomize the inputs or use the file input.

// IR
`define NUM_IR_TEST 64				// Upper bound of the random number generator.
`define IR_GEN_RAND_INST 1			// Lower bound of the random number generator.

// MUX
`define NUM_MUX_TEST  64			// Number of tests the Mux will perform.
`define MUX_UPPER_BOUND 64			// Upper bound of the random number generator.
`define MUX_LOWER_BOUND 0			// Lower bound of the random number generator.

// PC
`define NUM_PC_TEST 64				// Number of tests the PC will perform.
`define DREG_UPPER_BOUND 64			// Upper bound of the random number generator.
`define DREG_LOWER_BOUND 0			// Lower bound of the random number generator.

// RAM
`define NUM_RAM_TEST 64				// Number of tests the RAM will perform.
`define RAM_GEN_RAND_INPUT 1'b1			// Selects whether to randomize the inputs or use the file input.

Modules/MUX.v
module MUX(True, False, Cond, Out);
	`include "parameters.v"
	
	input [`DATA_WIDTH-1:0] True, False;
	input Cond;
	output reg [`DATA_WIDTH-1:0] Out;
	
	always @(*) begin
		Out = Cond ? True : False;
	end
endmodule

Testbenches/MUX_tb.v
module MUX_tb();
	`include "parameters.v"
	/*
		Control Signal:
			Cond - Selects the data that will pass through.
	*/
	reg Cond=0;
	/*
		Inputs:
			True - Is the data that will be passed through if the condition is true.
			False - Is the data that will be passed through if the condition is false.
	*/
        reg [`DATA_WIDTH-1:0] True=0, False=0;
	/*
		Output:
			Out - The output.
	*/
        wire [`DATA_WIDTH-1:0] Out;

	MUX multiplexor(
		.True(True),
		.False(False),
		.Cond(Cond),
		.Out(Out)	
	);

	integer file;
	integer test;
	initial begin
		$dumpfile("Junk/MUX.vcd");
		$dumpvars(0, MUX_tb);
		file = $fopen("Results/MUX.r", "w");
		for(test = 0; test < `NUM_MUX_TEST; test = test + 1) begin
			Cond = $urandom % 2;	// Generates a unsigned value between 0-1.
			True = $urandom % (`MUX_UPPER_BOUND-`MUX_LOWER_BOUND+1)+`MUX_LOWER_BOUND;
			False = $urandom % (`MUX_UPPER_BOUND-`MUX_LOWER_BOUND+1)+`MUX_LOWER_BOUND;
			#5;
			$fwrite(file, "Test = %d", test);
			$fwrite(file, "\tCond = %d", Cond);
			$fwrite(file, "\tTrue = %d", True);
			$fwrite(file, "\tFalse = %d", False);
			$fwrite(file, "\tOut = %d\n\n", Out);
		end
		#(2*`PERIOD*`NUM_MUX_TEST);
		$fclose(file);
		$finish();
		$stop;
	end
endmodule

Junk/MUX.vcd
$date
	Sat Dec 16 12:29:02 2023
$end
$version
	Icarus Verilog
$end
$timescale
	1s
$end
$scope module MUX_tb $end
$var wire 6 ! Out [5:0] $end
$var reg 1 " Cond $end
$var reg 6 # False [5:0] $end
$var reg 6 $ True [5:0] $end
$var integer 32 % file [31:0] $end
$var integer 32 & test [31:0] $end
$scope module multiplexor $end
$var wire 1 " Cond $end
$var wire 6 ' False [5:0] $end
$var wire 6 ( True [5:0] $end
$var reg 6 ) Out [5:0] $end
$upscope $end
$upscope $end
$enddefinitions $end
#0
$dumpvars
b100010 )
b111011 (
b100010 '
b0 &
b10000000000000000000000000000011 %
b111011 $
b100010 #
0"
b100010 !
$end
#5
b1111 !
b1111 )
b101101 #
b101101 '
b1111 $
b1111 (
1"
b1 &
#10
b111011 !
b111011 )
b110110 #
b110110 '
b111011 $
b111011 (
b10 &
#15
b11111 !
b11111 )
b11110 #
b11110 '
b11111 $
b11111 (
b11 &
#20
b101 !
b101 )
b101010 #
b101010 '
b101 $
b101 (
b100 &
#25
b101100 !
b101100 )
b101100 #
b101100 '
b1110 $
b1110 (
0"
b101 &
#30
b11011 !
b11011 )
b100100 #
b100100 '
b11011 $
b11011 (
1"
b110 &
#35
b111011 !
b111011 )
b100101 #
b100101 '
b111011 $
b111011 (
b111 &
#40
b10001 !
b10001 )
b10001 #
b10001 '
b11110 $
b11110 (
0"
b1000 &
#45
b101110 !
b101110 )
b110 #
b110 '
b101110 $
b101110 (
1"
b1001 &
#50
b1101 !
b1101 )
b11001 #
b11001 '
b1101 $
b1101 (
b1010 &
#55
b10010 !
b10010 )
b10010 #
b10010 '
b1100 $
b1100 (
0"
b1011 &
#60
b1000 !
b1000 )
b1000 #
b1000 '
b10111 $
b10111 (
b1100 &
#65
b111111 !
b111111 )
b1100 #
b1100 '
b111111 $
b111111 (
1"
b1101 &
#70
b100 !
b100 )
b100 #
b100 '
b11000 $
b11000 (
0"
b1110 &
#75
b110010 !
b110010 )
b1101 #
b1101 '
b110010 $
b110010 (
1"
b1111 &
#80
b100010 !
b100010 )
b100010 #
b100010 '
0"
b10000 &
#85
b10000 !
b10000 )
b10000 #
b10000 '
b101101 $
b101101 (
b10001 &
#90
b101 !
b101 )
b101 #
b101 '
b1 $
b1 (
b10010 &
#95
b0 !
b0 )
b0 #
b0 '
b101100 $
b101100 (
b10011 &
#100
b101101 !
b101101 )
b101101 #
b101101 '
b10 $
b10 (
b10100 &
#105
b100111 !
b100111 )
b1000 #
b1000 '
b100111 $
b100111 (
1"
b10101 &
#110
b101010 !
b101010 )
b11101 #
b11101 '
b101010 $
b101010 (
b10110 &
#115
b11010 !
b11010 )
b110001 #
b110001 '
b11010 $
b11010 (
b10111 &
#120
b10 !
b10 )
b10 #
b10 '
b10101 $
b10101 (
0"
b11000 &
#125
b1000 !
b1000 )
b110010 #
b110010 '
b1000 $
b1000 (
1"
b11001 &
#130
b110011 !
b110011 )
b10000 #
b10000 '
b110011 $
b110011 (
b11010 &
#135
b11100 !
b11100 )
b100111 #
b100111 '
b11100 $
b11100 (
b11011 &
#140
b10110 !
b10110 )
b101011 #
b101011 '
b10110 $
b10110 (
b11100 &
#145
b11011 !
b11011 )
b11011 #
b11011 '
b101001 $
b101001 (
0"
b11101 &
#150
b10111 !
b10111 )
b111000 #
b111000 '
b10111 $
b10111 (
1"
b11110 &
#155
b11111 !
b11111 )
b11111 #
b11111 '
b111011 $
b111011 (
0"
b11111 &
#160
b100101 !
b100101 )
b100100 #
b100100 '
b100101 $
b100101 (
1"
b100000 &
#165
b10000 !
b10000 )
b10000 #
b10000 '
b10000 $
b10000 (
0"
b100001 &
#170
b1000 !
b1000 )
b101 #
b101 '
b1000 $
b1000 (
1"
b100010 &
#175
b10010 !
b10010 )
b10010 #
b10010 '
b111101 $
b111101 (
0"
b100011 &
#180
b1000 !
b1000 )
b1000 #
b1000 '
b101 $
b101 (
b100100 &
#185
b11010 !
b11010 )
b110110 #
b110110 '
b11010 $
b11010 (
1"
b100101 &
#190
b110110 !
b110110 )
b1001 #
b1001 '
b110110 $
b110110 (
b100110 &
#195
b111100 !
b111100 )
b11011 #
b11011 '
b111100 $
b111100 (
b100111 &
#200
b100100 !
b100100 )
b110101 #
b110101 '
b100100 $
b100100 (
b101000 &
#205
b1111 !
b1111 )
b110100 #
b110100 '
b1111 $
b1111 (
b101001 &
#210
b111011 !
b111011 )
b101000 #
b101000 '
b111011 $
b111011 (
b101010 &
#215
b111001 !
b111001 )
b111001 #
b111001 '
b110101 $
b110101 (
0"
b101011 &
#220
b101110 !
b101110 )
b101110 #
b101110 '
b1000 $
b1000 (
b101100 &
#225
b110101 !
b110101 )
b1110 #
b1110 '
b110101 $
b110101 (
1"
b101101 &
#230
b110 !
b110 )
b111 #
b111 '
b110 $
b110 (
b101110 &
#235
b110010 !
b110010 )
b110010 #
b110010 '
b111010 $
b111010 (
0"
b101111 &
#240
b111010 !
b111010 )
b111010 #
b111010 '
b11000 $
b11000 (
b110000 &
#245
b100010 !
b100010 )
b1001 #
b1001 '
b100010 $
b100010 (
1"
b110001 &
#250
b100011 !
b100011 )
b110100 #
b110100 '
b100011 $
b100011 (
b110010 &
#255
b101001 !
b101001 )
b101001 #
b101001 '
b100 $
b100 (
0"
b110011 &
#260
b11001 !
b11001 )
b11001 #
b11001 '
b101 $
b101 (
b110100 &
#265
b110011 !
b110011 )
b101100 #
b101100 '
b110011 $
b110011 (
1"
b110101 &
#270
b1000 !
b1000 )
b1000 #
b1000 '
b1111 $
b1111 (
0"
b110110 &
#275
b11000 !
b11000 )
b11000 #
b11000 '
b11101 $
b11101 (
b110111 &
#280
b10101 #
b10101 '
b11000 $
b11000 (
1"
b111000 &
#285
b10001 !
b10001 )
b10001 #
b10001 '
b10110 $
b10110 (
0"
b111001 &
#290
b101110 !
b101110 )
b101110 #
b101110 '
b11101 $
b11101 (
b111010 &
#295
b110010 !
b110010 )
b110010 #
b110010 '
b11010 $
b11010 (
b111011 &
#300
b10101 !
b10101 )
b10110 #
b10110 '
b10101 $
b10101 (
1"
b111100 &
#305
b101010 !
b101010 )
b11010 #
b11010 '
b101010 $
b101010 (
b111101 &
#310
b11101 !
b11101 )
b11101 #
b11101 '
b110110 $
b110110 (
0"
b111110 &
#315
b110011 !
b110011 )
b110011 #
b110011 '
b100110 $
b100110 (
b111111 &
#320
b1000000 &
